{"py/object": "ExtractFunc.ExtractDataManager.StoreData", "folderPaths": ["D:/_EVENTS_/_Clair_/app\u6d4b\u8bd5", "D:/_EVENTS_/_Clair_/app\u6d4b\u8bd5-2"], "file_keywords": ["111", "222"], "keywords": ["123", "234", "345"], "tagGroups": [{"py/object": "ExtractFunc.ExtractDataManager.TagGroup", "groupName": "\u6708\u62a5", "tagList": [{"py/object": "ExtractFunc.ExtractDataManager.Tag", "tagInfo": {"\u540d\u79f0": "123", "\u5750\u6807": "", "\u5173\u952e\u8bcd": "", "\u5355\u4f4d": ""}, "isActive": true}, {"py/object": "ExtractFunc.ExtractDataManager.Tag", "tagInfo": {"\u540d\u79f0": "\u6807\u7b7e2", "\u5750\u6807": "", "\u5173\u952e\u8bcd": "", "\u5355\u4f4d": ""}, "isActive": true}, {"py/object": "ExtractFunc.ExtractDataManager.Tag", "tagInfo": {"\u540d\u79f0": "\u6807\u7b7e3", "\u5750\u6807": "", "\u5173\u952e\u8bcd": "456", "\u5355\u4f4d": ""}, "isActive": true}]}, {"py/object": "ExtractFunc.ExtractDataManager.TagGroup", "groupName": "\u5e74\u62a5", "tagList": [{"py/object": "ExtractFunc.ExtractDataManager.Tag", "tagInfo": {"\u540d\u79f0": "\u6807\u7b7e1", "\u5750\u6807": "", "\u5173\u952e\u8bcd": "", "\u5355\u4f4d": ""}, "isActive": false}, {"py/object": "ExtractFunc.ExtractDataManager.Tag", "tagInfo": {"\u540d\u79f0": "hhh", "\u5750\u6807": "", "\u5173\u952e\u8bcd": "", "\u5355\u4f4d": ""}, "isActive": true}, {"py/object": "ExtractFunc.ExtractDataManager.Tag", "tagInfo": {"\u540d\u79f0": "\u6807\u7b7e3", "\u5750\u6807": "", "\u5173\u952e\u8bcd": "hhh", "\u5355\u4f4d": ""}, "isActive": false}, {"py/object": "ExtractFunc.ExtractDataManager.Tag", "tagInfo": {"\u540d\u79f0": "\u6807\u7b7e4", "\u5750\u6807": "", "\u5173\u952e\u8bcd": "", "\u5355\u4f4d": ""}, "isActive": true}]}, {"py/object": "ExtractFunc.ExtractDataManager.TagGroup", "groupName": "123", "tagList": [{"py/object": "ExtractFunc.ExtractDataManager.Tag", "tagInfo": {"\u540d\u79f0": "\u6807\u7b7e1", "\u5750\u6807": "", "\u5173\u952e\u8bcd": "", "\u5355\u4f4d": ""}, "isActive": true}]}], "activeGroup": 0, "followRow": true, "autoAttange": true}